{
    "version": "1.2.27",
    "description": "CLI toolchain for Fedify and debugging ActivityPub",
    "homepage": "https://fedify.dev/cli",
    "license": "MIT",
    "architecture": {
        "64bit": {
            "url": "https://github.com/fedify-dev/fedify/releases/download/1.2.27/fedify-cli-1.2.27-windows-x86_64.zip",
            "hash": "e5c317147ac63341045b683c80c8207a7f41259569a3ff28157b668d2c8ff08a"
        }
    },
    "bin": "fedify.exe",
    "checkver": {
        "github": "https://github.com/fedify-dev/fedify"
    },
    "autoupdate": {
        "architecture": {
            "64bit": {
                "url": "https://github.com/fedify-dev/fedify/releases/download/$version/fedify-cli-$version-windows-x86_64.zip"
            }
        }
    }
}
